{
 "Resources": {
  "GetProductsListServiceRole773AEB2D": {
   "Type": "AWS::IAM::Role",
   "Properties": {
    "AssumeRolePolicyDocument": {
     "Statement": [
      {
       "Action": "sts:AssumeRole",
       "Effect": "Allow",
       "Principal": {
        "Service": "lambda.amazonaws.com"
       }
      }
     ],
     "Version": "2012-10-17"
    },
    "ManagedPolicyArns": [
     {
      "Fn::Join": [
       "",
       [
        "arn:",
        {
         "Ref": "AWS::Partition"
        },
        ":iam::aws:policy/service-role/AWSLambdaBasicExecutionRole"
       ]
      ]
     }
    ]
   },
   "Metadata": {
    "aws:cdk:path": "ProductsServiceStack/GetProductsList/ServiceRole/Resource"
   }
  },
  "GetProductsList379A1E5D": {
   "Type": "AWS::Lambda::Function",
   "Properties": {
    "Code": {
     "S3Bucket": {
      "Fn::Sub": "cdk-hnb659fds-assets-${AWS::AccountId}-${AWS::Region}"
     },
     "S3Key": "7b53e6db8e262afdf976e64ddbec7ebfcdeffbd00aafcf03193dda523873898f.zip"
    },
    "Handler": "getProductsList.handler",
    "Role": {
     "Fn::GetAtt": [
      "GetProductsListServiceRole773AEB2D",
      "Arn"
     ]
    },
    "Runtime": "nodejs20.x"
   },
   "DependsOn": [
    "GetProductsListServiceRole773AEB2D"
   ],
   "Metadata": {
    "aws:cdk:path": "ProductsServiceStack/GetProductsList/Resource",
    "aws:asset:path": "asset.7b53e6db8e262afdf976e64ddbec7ebfcdeffbd00aafcf03193dda523873898f",
    "aws:asset:is-bundled": false,
    "aws:asset:property": "Code"
   }
  },
  "GetProductByIDServiceRoleE265ED01": {
   "Type": "AWS::IAM::Role",
   "Properties": {
    "AssumeRolePolicyDocument": {
     "Statement": [
      {
       "Action": "sts:AssumeRole",
       "Effect": "Allow",
       "Principal": {
        "Service": "lambda.amazonaws.com"
       }
      }
     ],
     "Version": "2012-10-17"
    },
    "ManagedPolicyArns": [
     {
      "Fn::Join": [
       "",
       [
        "arn:",
        {
         "Ref": "AWS::Partition"
        },
        ":iam::aws:policy/service-role/AWSLambdaBasicExecutionRole"
       ]
      ]
     }
    ]
   },
   "Metadata": {
    "aws:cdk:path": "ProductsServiceStack/GetProductByID/ServiceRole/Resource"
   }
  },
  "GetProductByID012467D4": {
   "Type": "AWS::Lambda::Function",
   "Properties": {
    "Code": {
     "S3Bucket": {
      "Fn::Sub": "cdk-hnb659fds-assets-${AWS::AccountId}-${AWS::Region}"
     },
     "S3Key": "7b53e6db8e262afdf976e64ddbec7ebfcdeffbd00aafcf03193dda523873898f.zip"
    },
    "Handler": "getProductById.handler",
    "Role": {
     "Fn::GetAtt": [
      "GetProductByIDServiceRoleE265ED01",
      "Arn"
     ]
    },
    "Runtime": "nodejs20.x"
   },
   "DependsOn": [
    "GetProductByIDServiceRoleE265ED01"
   ],
   "Metadata": {
    "aws:cdk:path": "ProductsServiceStack/GetProductByID/Resource",
    "aws:asset:path": "asset.7b53e6db8e262afdf976e64ddbec7ebfcdeffbd00aafcf03193dda523873898f",
    "aws:asset:is-bundled": false,
    "aws:asset:property": "Code"
   }
  },
  "ProductsAPI63F140D0": {
   "Type": "AWS::ApiGateway::RestApi",
   "Properties": {
    "Description": "This service serves products for RSS AWS course.",
    "Name": "ProductsService"
   },
   "Metadata": {
    "aws:cdk:path": "ProductsServiceStack/ProductsAPI/Resource"
   }
  },
  "ProductsAPIDeployment6846F2A7d0f66248dd157e7d800903de290e92ba": {
   "Type": "AWS::ApiGateway::Deployment",
   "Properties": {
    "Description": "This service serves products for RSS AWS course.",
    "RestApiId": {
     "Ref": "ProductsAPI63F140D0"
    }
   },
   "DependsOn": [
    "ProductsAPIOPTIONSD2A48733",
    "ProductsAPIproductsidGET708AF44E",
    "ProductsAPIproductsidOPTIONS311A785B",
    "ProductsAPIproductsid3B20EBA5",
    "ProductsAPIproductsGETDF356BB7",
    "ProductsAPIproductsOPTIONSCF3A9D9B",
    "ProductsAPIproductsDFDB6098"
   ],
   "Metadata": {
    "aws:cdk:path": "ProductsServiceStack/ProductsAPI/Deployment/Resource"
   }
  },
  "ProductsAPIDeploymentStageprod9783ADE4": {
   "Type": "AWS::ApiGateway::Stage",
   "Properties": {
    "DeploymentId": {
     "Ref": "ProductsAPIDeployment6846F2A7d0f66248dd157e7d800903de290e92ba"
    },
    "RestApiId": {
     "Ref": "ProductsAPI63F140D0"
    },
    "StageName": "prod"
   },
   "Metadata": {
    "aws:cdk:path": "ProductsServiceStack/ProductsAPI/DeploymentStage.prod/Resource"
   }
  },
  "ProductsAPIOPTIONSD2A48733": {
   "Type": "AWS::ApiGateway::Method",
   "Properties": {
    "ApiKeyRequired": false,
    "AuthorizationType": "NONE",
    "HttpMethod": "OPTIONS",
    "Integration": {
     "IntegrationResponses": [
      {
       "ResponseParameters": {
        "method.response.header.Access-Control-Allow-Headers": "'Content-Type,X-Amz-Date,Authorization,X-Api-Key,X-Amz-Security-Token,X-Amz-User-Agent'",
        "method.response.header.Access-Control-Allow-Origin": "'*'",
        "method.response.header.Access-Control-Allow-Methods": "'OPTIONS,GET,PUT,POST,DELETE,PATCH,HEAD'"
       },
       "StatusCode": "204"
      }
     ],
     "RequestTemplates": {
      "application/json": "{ statusCode: 200 }"
     },
     "Type": "MOCK"
    },
    "MethodResponses": [
     {
      "ResponseParameters": {
       "method.response.header.Access-Control-Allow-Headers": true,
       "method.response.header.Access-Control-Allow-Origin": true,
       "method.response.header.Access-Control-Allow-Methods": true
      },
      "StatusCode": "204"
     }
    ],
    "ResourceId": {
     "Fn::GetAtt": [
      "ProductsAPI63F140D0",
      "RootResourceId"
     ]
    },
    "RestApiId": {
     "Ref": "ProductsAPI63F140D0"
    }
   },
   "Metadata": {
    "aws:cdk:path": "ProductsServiceStack/ProductsAPI/Default/OPTIONS/Resource"
   }
  },
  "ProductsAPIproductsDFDB6098": {
   "Type": "AWS::ApiGateway::Resource",
   "Properties": {
    "ParentId": {
     "Fn::GetAtt": [
      "ProductsAPI63F140D0",
      "RootResourceId"
     ]
    },
    "PathPart": "products",
    "RestApiId": {
     "Ref": "ProductsAPI63F140D0"
    }
   },
   "Metadata": {
    "aws:cdk:path": "ProductsServiceStack/ProductsAPI/Default/products/Resource"
   }
  },
  "ProductsAPIproductsOPTIONSCF3A9D9B": {
   "Type": "AWS::ApiGateway::Method",
   "Properties": {
    "ApiKeyRequired": false,
    "AuthorizationType": "NONE",
    "HttpMethod": "OPTIONS",
    "Integration": {
     "IntegrationResponses": [
      {
       "ResponseParameters": {
        "method.response.header.Access-Control-Allow-Headers": "'Content-Type,X-Amz-Date,Authorization,X-Api-Key,X-Amz-Security-Token,X-Amz-User-Agent'",
        "method.response.header.Access-Control-Allow-Origin": "'*'",
        "method.response.header.Access-Control-Allow-Methods": "'OPTIONS,GET,PUT,POST,DELETE,PATCH,HEAD'"
       },
       "StatusCode": "204"
      }
     ],
     "RequestTemplates": {
      "application/json": "{ statusCode: 200 }"
     },
     "Type": "MOCK"
    },
    "MethodResponses": [
     {
      "ResponseParameters": {
       "method.response.header.Access-Control-Allow-Headers": true,
       "method.response.header.Access-Control-Allow-Origin": true,
       "method.response.header.Access-Control-Allow-Methods": true
      },
      "StatusCode": "204"
     }
    ],
    "ResourceId": {
     "Ref": "ProductsAPIproductsDFDB6098"
    },
    "RestApiId": {
     "Ref": "ProductsAPI63F140D0"
    }
   },
   "Metadata": {
    "aws:cdk:path": "ProductsServiceStack/ProductsAPI/Default/products/OPTIONS/Resource"
   }
  },
  "ProductsAPIproductsGETApiPermissionProductsServiceStackProductsAPIBAAEF789GETproductsBD2CC933": {
   "Type": "AWS::Lambda::Permission",
   "Properties": {
    "Action": "lambda:InvokeFunction",
    "FunctionName": {
     "Fn::GetAtt": [
      "GetProductsList379A1E5D",
      "Arn"
     ]
    },
    "Principal": "apigateway.amazonaws.com",
    "SourceArn": {
     "Fn::Join": [
      "",
      [
       "arn:",
       {
        "Ref": "AWS::Partition"
       },
       ":execute-api:",
       {
        "Ref": "AWS::Region"
       },
       ":",
       {
        "Ref": "AWS::AccountId"
       },
       ":",
       {
        "Ref": "ProductsAPI63F140D0"
       },
       "/",
       {
        "Ref": "ProductsAPIDeploymentStageprod9783ADE4"
       },
       "/GET/products"
      ]
     ]
    }
   },
   "Metadata": {
    "aws:cdk:path": "ProductsServiceStack/ProductsAPI/Default/products/GET/ApiPermission.ProductsServiceStackProductsAPIBAAEF789.GET..products"
   }
  },
  "ProductsAPIproductsGETApiPermissionTestProductsServiceStackProductsAPIBAAEF789GETproducts27CB0D8A": {
   "Type": "AWS::Lambda::Permission",
   "Properties": {
    "Action": "lambda:InvokeFunction",
    "FunctionName": {
     "Fn::GetAtt": [
      "GetProductsList379A1E5D",
      "Arn"
     ]
    },
    "Principal": "apigateway.amazonaws.com",
    "SourceArn": {
     "Fn::Join": [
      "",
      [
       "arn:",
       {
        "Ref": "AWS::Partition"
       },
       ":execute-api:",
       {
        "Ref": "AWS::Region"
       },
       ":",
       {
        "Ref": "AWS::AccountId"
       },
       ":",
       {
        "Ref": "ProductsAPI63F140D0"
       },
       "/test-invoke-stage/GET/products"
      ]
     ]
    }
   },
   "Metadata": {
    "aws:cdk:path": "ProductsServiceStack/ProductsAPI/Default/products/GET/ApiPermission.Test.ProductsServiceStackProductsAPIBAAEF789.GET..products"
   }
  },
  "ProductsAPIproductsGETDF356BB7": {
   "Type": "AWS::ApiGateway::Method",
   "Properties": {
    "AuthorizationType": "NONE",
    "HttpMethod": "GET",
    "Integration": {
     "IntegrationHttpMethod": "POST",
     "Type": "AWS_PROXY",
     "Uri": {
      "Fn::Join": [
       "",
       [
        "arn:",
        {
         "Ref": "AWS::Partition"
        },
        ":apigateway:",
        {
         "Ref": "AWS::Region"
        },
        ":lambda:path/2015-03-31/functions/",
        {
         "Fn::GetAtt": [
          "GetProductsList379A1E5D",
          "Arn"
         ]
        },
        "/invocations"
       ]
      ]
     }
    },
    "ResourceId": {
     "Ref": "ProductsAPIproductsDFDB6098"
    },
    "RestApiId": {
     "Ref": "ProductsAPI63F140D0"
    }
   },
   "Metadata": {
    "aws:cdk:path": "ProductsServiceStack/ProductsAPI/Default/products/GET/Resource"
   }
  },
  "ProductsAPIproductsid3B20EBA5": {
   "Type": "AWS::ApiGateway::Resource",
   "Properties": {
    "ParentId": {
     "Ref": "ProductsAPIproductsDFDB6098"
    },
    "PathPart": "{id}",
    "RestApiId": {
     "Ref": "ProductsAPI63F140D0"
    }
   },
   "Metadata": {
    "aws:cdk:path": "ProductsServiceStack/ProductsAPI/Default/products/{id}/Resource"
   }
  },
  "ProductsAPIproductsidOPTIONS311A785B": {
   "Type": "AWS::ApiGateway::Method",
   "Properties": {
    "ApiKeyRequired": false,
    "AuthorizationType": "NONE",
    "HttpMethod": "OPTIONS",
    "Integration": {
     "IntegrationResponses": [
      {
       "ResponseParameters": {
        "method.response.header.Access-Control-Allow-Headers": "'Content-Type,X-Amz-Date,Authorization,X-Api-Key,X-Amz-Security-Token,X-Amz-User-Agent'",
        "method.response.header.Access-Control-Allow-Origin": "'*'",
        "method.response.header.Access-Control-Allow-Methods": "'OPTIONS,GET,PUT,POST,DELETE,PATCH,HEAD'"
       },
       "StatusCode": "204"
      }
     ],
     "RequestTemplates": {
      "application/json": "{ statusCode: 200 }"
     },
     "Type": "MOCK"
    },
    "MethodResponses": [
     {
      "ResponseParameters": {
       "method.response.header.Access-Control-Allow-Headers": true,
       "method.response.header.Access-Control-Allow-Origin": true,
       "method.response.header.Access-Control-Allow-Methods": true
      },
      "StatusCode": "204"
     }
    ],
    "ResourceId": {
     "Ref": "ProductsAPIproductsid3B20EBA5"
    },
    "RestApiId": {
     "Ref": "ProductsAPI63F140D0"
    }
   },
   "Metadata": {
    "aws:cdk:path": "ProductsServiceStack/ProductsAPI/Default/products/{id}/OPTIONS/Resource"
   }
  },
  "ProductsAPIproductsidGETApiPermissionProductsServiceStackProductsAPIBAAEF789GETproductsidADEB9B93": {
   "Type": "AWS::Lambda::Permission",
   "Properties": {
    "Action": "lambda:InvokeFunction",
    "FunctionName": {
     "Fn::GetAtt": [
      "GetProductByID012467D4",
      "Arn"
     ]
    },
    "Principal": "apigateway.amazonaws.com",
    "SourceArn": {
     "Fn::Join": [
      "",
      [
       "arn:",
       {
        "Ref": "AWS::Partition"
       },
       ":execute-api:",
       {
        "Ref": "AWS::Region"
       },
       ":",
       {
        "Ref": "AWS::AccountId"
       },
       ":",
       {
        "Ref": "ProductsAPI63F140D0"
       },
       "/",
       {
        "Ref": "ProductsAPIDeploymentStageprod9783ADE4"
       },
       "/GET/products/*"
      ]
     ]
    }
   },
   "Metadata": {
    "aws:cdk:path": "ProductsServiceStack/ProductsAPI/Default/products/{id}/GET/ApiPermission.ProductsServiceStackProductsAPIBAAEF789.GET..products.{id}"
   }
  },
  "ProductsAPIproductsidGETApiPermissionTestProductsServiceStackProductsAPIBAAEF789GETproductsid793C9C55": {
   "Type": "AWS::Lambda::Permission",
   "Properties": {
    "Action": "lambda:InvokeFunction",
    "FunctionName": {
     "Fn::GetAtt": [
      "GetProductByID012467D4",
      "Arn"
     ]
    },
    "Principal": "apigateway.amazonaws.com",
    "SourceArn": {
     "Fn::Join": [
      "",
      [
       "arn:",
       {
        "Ref": "AWS::Partition"
       },
       ":execute-api:",
       {
        "Ref": "AWS::Region"
       },
       ":",
       {
        "Ref": "AWS::AccountId"
       },
       ":",
       {
        "Ref": "ProductsAPI63F140D0"
       },
       "/test-invoke-stage/GET/products/*"
      ]
     ]
    }
   },
   "Metadata": {
    "aws:cdk:path": "ProductsServiceStack/ProductsAPI/Default/products/{id}/GET/ApiPermission.Test.ProductsServiceStackProductsAPIBAAEF789.GET..products.{id}"
   }
  },
  "ProductsAPIproductsidGET708AF44E": {
   "Type": "AWS::ApiGateway::Method",
   "Properties": {
    "AuthorizationType": "NONE",
    "HttpMethod": "GET",
    "Integration": {
     "IntegrationHttpMethod": "POST",
     "Type": "AWS_PROXY",
     "Uri": {
      "Fn::Join": [
       "",
       [
        "arn:",
        {
         "Ref": "AWS::Partition"
        },
        ":apigateway:",
        {
         "Ref": "AWS::Region"
        },
        ":lambda:path/2015-03-31/functions/",
        {
         "Fn::GetAtt": [
          "GetProductByID012467D4",
          "Arn"
         ]
        },
        "/invocations"
       ]
      ]
     }
    },
    "ResourceId": {
     "Ref": "ProductsAPIproductsid3B20EBA5"
    },
    "RestApiId": {
     "Ref": "ProductsAPI63F140D0"
    }
   },
   "Metadata": {
    "aws:cdk:path": "ProductsServiceStack/ProductsAPI/Default/products/{id}/GET/Resource"
   }
  },
  "CDKMetadata": {
   "Type": "AWS::CDK::Metadata",
   "Properties": {
    "Analytics": "v2:deflate64:H4sIAAAAAAAA/02P0W6DMAxFv6XvwYO22nvbaW/TJvoBlQsecyEJwk5Rhfj3KSnTeLonvs61vYVi/wr5BkfJqrrNOr7CdFasWoOjXKYO7bVGmN6Dq5S9M6dvt+YvGiyLsHezYbQwlb6jaESdjewuKEIqcIhiZAfHULWkRxQy2HODSiM+YCpJ9NBz+rrgG/Wdf1hyGqur11mxSUOeUJL4MFSUMj9If3wdzYX+3CU58Tz/l9NiMYhdE3s+g/ZB192RT97VrOlM52uCm7zctzkUBeSbmzBnQ3DKlqB86i8uGsRZWAEAAA=="
   },
   "Metadata": {
    "aws:cdk:path": "ProductsServiceStack/CDKMetadata/Default"
   },
   "Condition": "CDKMetadataAvailable"
  }
 },
 "Outputs": {
  "ProductsAPIEndpointEFF809AE": {
   "Value": {
    "Fn::Join": [
     "",
     [
      "https://",
      {
       "Ref": "ProductsAPI63F140D0"
      },
      ".execute-api.",
      {
       "Ref": "AWS::Region"
      },
      ".",
      {
       "Ref": "AWS::URLSuffix"
      },
      "/",
      {
       "Ref": "ProductsAPIDeploymentStageprod9783ADE4"
      },
      "/"
     ]
    ]
   }
  }
 },
 "Conditions": {
  "CDKMetadataAvailable": {
   "Fn::Or": [
    {
     "Fn::Or": [
      {
       "Fn::Equals": [
        {
         "Ref": "AWS::Region"
        },
        "af-south-1"
       ]
      },
      {
       "Fn::Equals": [
        {
         "Ref": "AWS::Region"
        },
        "ap-east-1"
       ]
      },
      {
       "Fn::Equals": [
        {
         "Ref": "AWS::Region"
        },
        "ap-northeast-1"
       ]
      },
      {
       "Fn::Equals": [
        {
         "Ref": "AWS::Region"
        },
        "ap-northeast-2"
       ]
      },
      {
       "Fn::Equals": [
        {
         "Ref": "AWS::Region"
        },
        "ap-south-1"
       ]
      },
      {
       "Fn::Equals": [
        {
         "Ref": "AWS::Region"
        },
        "ap-southeast-1"
       ]
      },
      {
       "Fn::Equals": [
        {
         "Ref": "AWS::Region"
        },
        "ap-southeast-2"
       ]
      },
      {
       "Fn::Equals": [
        {
         "Ref": "AWS::Region"
        },
        "ca-central-1"
       ]
      },
      {
       "Fn::Equals": [
        {
         "Ref": "AWS::Region"
        },
        "cn-north-1"
       ]
      },
      {
       "Fn::Equals": [
        {
         "Ref": "AWS::Region"
        },
        "cn-northwest-1"
       ]
      }
     ]
    },
    {
     "Fn::Or": [
      {
       "Fn::Equals": [
        {
         "Ref": "AWS::Region"
        },
        "eu-central-1"
       ]
      },
      {
       "Fn::Equals": [
        {
         "Ref": "AWS::Region"
        },
        "eu-north-1"
       ]
      },
      {
       "Fn::Equals": [
        {
         "Ref": "AWS::Region"
        },
        "eu-south-1"
       ]
      },
      {
       "Fn::Equals": [
        {
         "Ref": "AWS::Region"
        },
        "eu-west-1"
       ]
      },
      {
       "Fn::Equals": [
        {
         "Ref": "AWS::Region"
        },
        "eu-west-2"
       ]
      },
      {
       "Fn::Equals": [
        {
         "Ref": "AWS::Region"
        },
        "eu-west-3"
       ]
      },
      {
       "Fn::Equals": [
        {
         "Ref": "AWS::Region"
        },
        "il-central-1"
       ]
      },
      {
       "Fn::Equals": [
        {
         "Ref": "AWS::Region"
        },
        "me-central-1"
       ]
      },
      {
       "Fn::Equals": [
        {
         "Ref": "AWS::Region"
        },
        "me-south-1"
       ]
      },
      {
       "Fn::Equals": [
        {
         "Ref": "AWS::Region"
        },
        "sa-east-1"
       ]
      }
     ]
    },
    {
     "Fn::Or": [
      {
       "Fn::Equals": [
        {
         "Ref": "AWS::Region"
        },
        "us-east-1"
       ]
      },
      {
       "Fn::Equals": [
        {
         "Ref": "AWS::Region"
        },
        "us-east-2"
       ]
      },
      {
       "Fn::Equals": [
        {
         "Ref": "AWS::Region"
        },
        "us-west-1"
       ]
      },
      {
       "Fn::Equals": [
        {
         "Ref": "AWS::Region"
        },
        "us-west-2"
       ]
      }
     ]
    }
   ]
  }
 },
 "Parameters": {
  "BootstrapVersion": {
   "Type": "AWS::SSM::Parameter::Value<String>",
   "Default": "/cdk-bootstrap/hnb659fds/version",
   "Description": "Version of the CDK Bootstrap resources in this environment, automatically retrieved from SSM Parameter Store. [cdk:skip]"
  }
 },
 "Rules": {
  "CheckBootstrapVersion": {
   "Assertions": [
    {
     "Assert": {
      "Fn::Not": [
       {
        "Fn::Contains": [
         [
          "1",
          "2",
          "3",
          "4",
          "5"
         ],
         {
          "Ref": "BootstrapVersion"
         }
        ]
       }
      ]
     },
     "AssertDescription": "CDK bootstrap stack version 6 required. Please run 'cdk bootstrap' with a recent version of the CDK CLI."
    }
   ]
  }
 }
}